{
  "date": "2025-05-13",
  "sleep": {
    "dailySleepDTO": {
      "id": 1747081709000,
      "userProfilePK": 2405885,
      "calendarDate": "2025-05-13",
      "sleepTimeSeconds": 27140,
      "napTimeSeconds": 0,
      "sleepWindowConfirmed": true,
      "sleepWindowConfirmationType": "enhanced_confirmed_final",
      "sleepStartTimestampGMT": 1747081709000,
      "sleepEndTimestampGMT": 1747111129000,
      "sleepStartTimestampLocal": 1747088909000,
      "sleepEndTimestampLocal": 1747118329000,
      "autoSleepStartTimestampGMT": null,
      "autoSleepEndTimestampGMT": null,
      "sleepQualityTypePK": null,
      "sleepResultTypePK": null,
      "unmeasurableSleepSeconds": 0,
      "deepSleepSeconds": 2580,
      "lightSleepSeconds": 20040,
      "remSleepSeconds": 4560,
      "awakeSleepSeconds": 2280,
      "deviceRemCapable": true,
      "retro": false,
      "sleepFromDevice": true,
      "averageRespirationValue": 13,
      "lowestRespirationValue": 6,
      "highestRespirationValue": 20,
      "awakeCount": 2,
      "avgSleepStress": 19,
      "ageGroup": "ADULT",
      "sleepScoreFeedback": "POSITIVE_LONG_AND_CALM",
      "sleepScoreInsight": "NONE",
      "sleepScorePersonalizedInsight": "STRESS_POS_FAIR_OR_POOR_SLEEP_RESTFUL_DAY",
      "sleepScores": {
        "totalDuration": {
          "qualifierKey": "EXCELLENT",
          "optimalStart": 27600,
          "optimalEnd": 27600
        },
        "stress": {
          "qualifierKey": "FAIR",
          "optimalStart": 0,
          "optimalEnd": 15
        },
        "awakeCount": {
          "qualifierKey": "FAIR",
          "optimalStart": 0,
          "optimalEnd": 1
        },
        "overall": {
          "value": 78,
          "qualifierKey": "FAIR"
        },
        "remPercentage": {
          "value": 17,
          "qualifierKey": "FAIR",
          "optimalStart": 21,
          "optimalEnd": 31,
          "idealStartInSeconds": 5699.4,
          "idealEndInSeconds": 8413.4
        },
        "restlessness": {
          "qualifierKey": "FAIR",
          "optimalStart": 0,
          "optimalEnd": 5
        },
        "lightPercentage": {
          "value": 74,
          "qualifierKey": "FAIR",
          "optimalStart": 30,
          "optimalEnd": 64,
          "idealStartInSeconds": 8142,
          "idealEndInSeconds": 17369.6
        },
        "deepPercentage": {
          "value": 10,
          "qualifierKey": "FAIR",
          "optimalStart": 16,
          "optimalEnd": 33,
          "idealStartInSeconds": 4342.4,
          "idealEndInSeconds": 8956.2
        }
      },
      "sleepVersion": 2,
      "sleepNeed": {
        "userProfilePk": 2405885,
        "calendarDate": "2025-05-13",
        "deviceId": 3450369454,
        "timestampGmt": "2025-05-12T05:15:29",
        "baseline": 460,
        "actual": 530,
        "feedback": "HIGHLY_INCREASED",
        "trainingFeedback": "HIGH_ACWR_AND_CHRONIC",
        "sleepHistoryAdjustment": "INCREASING_LOW_QUALITY",
        "hrvAdjustment": "INCREASING",
        "napAdjustment": "NO_CHANGE",
        "displayedForTheDay": true,
        "preferredActivityTracker": true
      },
      "nextSleepNeed": {
        "userProfilePk": 2405885,
        "calendarDate": "2025-05-14",
        "deviceId": 3450369454,
        "timestampGmt": "2025-05-13T06:37:50",
        "baseline": 460,
        "actual": 510,
        "feedback": "HIGHLY_INCREASED",
        "trainingFeedback": "HIGH_ACWR_AND_CHRONIC",
        "sleepHistoryAdjustment": "INCREASING_LOW_QUALITY",
        "hrvAdjustment": "INCREASING",
        "napAdjustment": "NO_CHANGE",
        "displayedForTheDay": true,
        "preferredActivityTracker": true
      }
    },
    "sleepMovement": null,
    "remSleepData": true,
    "sleepLevels": null,
    "skinTempDataExists": true,
    "avgSkinTempDeviationC": -0.3,
    "avgSkinTempDeviationF": -0.5,
    "bodyBatteryChange": 53,
    "skinTempCalibrationDays": 19,
    "restingHeartRate": 52
  },
  "sleep_stats": {
    "overallStats": {
      "averageSpO2": null,
      "meanAvgHeartRate": null,
      "averageLocalSleepStartTime": -7431,
      "averageRespiration": 13,
      "averageBodyBatteryChange": 42,
      "averageSkinTempF": 0,
      "averageSleepScore": 70,
      "averageLocalSleepEndTime": 18138,
      "averageSkinTempC": 0,
      "averageSleepSeconds": 23923,
      "averageSleepNeed": 519,
      "averageRestingHeartRate": 51
    },
    "individualStats": [
      {
        "calendarDate": "2025-05-07",
        "values": {
          "remTime": 3660,
          "restingHeartRate": 48,
          "totalSleepTimeInSeconds": 21420,
          "respiration": 14,
          "localSleepEndTimeInMillis": 1746591608000,
          "deepTime": 2460,
          "awakeTime": 600,
          "sleepScoreQuality": "FAIR",
          "spO2": null,
          "localSleepStartTimeInMillis": 1746569588000,
          "sleepNeed": 540,
          "bodyBatteryChange": 31,
          "gmtSleepStartTimeInMillis": 1746562388000,
          "gmtSleepEndTimeInMillis": 1746584408000,
          "hrvStatus": "LOW",
          "skinTempF": -0.2,
          "sleepScore": 69,
          "skinTempC": -0.1,
          "lightTime": 15300,
          "avgOvernightHrv": 41,
          "avgHeartRate": null,
          "hrv7dAverage": 42
        }
      },
      {
        "calendarDate": "2025-05-08",
        "values": {
          "remTime": 2220,
          "restingHeartRate": 49,
          "totalSleepTimeInSeconds": 22440,
          "respiration": 13,
          "localSleepEndTimeInMillis": 1746678652000,
          "deepTime": 3180,
          "awakeTime": 2640,
          "sleepScoreQuality": "FAIR",
          "spO2": null,
          "localSleepStartTimeInMillis": 1746653572000,
          "sleepNeed": 530,
          "bodyBatteryChange": 48,
          "gmtSleepStartTimeInMillis": 1746646372000,
          "gmtSleepEndTimeInMillis": 1746671452000,
          "hrvStatus": "LOW",
          "skinTempF": -0.9,
          "sleepScore": 68,
          "skinTempC": -0.5,
          "lightTime": 17040,
          "avgOvernightHrv": 52,
          "avgHeartRate": null,
          "hrv7dAverage": 43
        }
      },
      {
        "calendarDate": "2025-05-09",
        "values": {
          "remTime": 2520,
          "restingHeartRate": 50,
          "totalSleepTimeInSeconds": 21420,
          "respiration": 13,
          "localSleepEndTimeInMillis": 1746763231000,
          "deepTime": 3060,
          "awakeTime": 480,
          "sleepScoreQuality": "FAIR",
          "spO2": null,
          "localSleepStartTimeInMillis": 1746741331000,
          "sleepNeed": 520,
          "bodyBatteryChange": 44,
          "gmtSleepStartTimeInMillis": 1746734131000,
          "gmtSleepEndTimeInMillis": 1746756031000,
          "hrvStatus": "UNBALANCED",
          "skinTempF": -0.4,
          "sleepScore": 72,
          "skinTempC": -0.2,
          "lightTime": 15840,
          "avgOvernightHrv": 57,
          "avgHeartRate": null,
          "hrv7dAverage": 46
        }
      },
      {
        "calendarDate": "2025-05-10",
        "values": {
          "remTime": 3600,
          "restingHeartRate": 55,
          "totalSleepTimeInSeconds": 27103,
          "respiration": 14,
          "localSleepEndTimeInMillis": 1746853697000,
          "deepTime": 3480,
          "awakeTime": 1800,
          "sleepScoreQuality": "FAIR",
          "spO2": null,
          "localSleepStartTimeInMillis": 1746824794000,
          "sleepNeed": 530,
          "bodyBatteryChange": 30,
          "gmtSleepStartTimeInMillis": 1746817594000,
          "gmtSleepEndTimeInMillis": 1746846497000,
          "hrvStatus": "UNBALANCED",
          "skinTempF": 0.9,
          "sleepScore": 65,
          "skinTempC": 0.5,
          "lightTime": 20040,
          "avgOvernightHrv": 39,
          "avgHeartRate": null,
          "hrv7dAverage": 46
        }
      },
      {
        "calendarDate": "2025-05-11",
        "values": {
          "remTime": 3960,
          "restingHeartRate": 52,
          "totalSleepTimeInSeconds": 25080,
          "respiration": 14,
          "localSleepEndTimeInMillis": 1746942088000,
          "deepTime": 4440,
          "awakeTime": 2400,
          "sleepScoreQuality": "FAIR",
          "spO2": null,
          "localSleepStartTimeInMillis": 1746914608000,
          "sleepNeed": 490,
          "bodyBatteryChange": 50,
          "gmtSleepStartTimeInMillis": 1746907408000,
          "gmtSleepEndTimeInMillis": 1746934888000,
          "hrvStatus": "UNBALANCED",
          "skinTempF": -0.1,
          "sleepScore": 75,
          "skinTempC": -0.1,
          "lightTime": 16680,
          "avgOvernightHrv": 45,
          "avgHeartRate": null,
          "hrv7dAverage": 47
        }
      },
      {
        "calendarDate": "2025-05-12",
        "values": {
          "remTime": 1260,
          "restingHeartRate": 50,
          "totalSleepTimeInSeconds": 22860,
          "respiration": 13,
          "localSleepEndTimeInMillis": 1747025759000,
          "deepTime": 3000,
          "awakeTime": 1320,
          "sleepScoreQuality": "FAIR",
          "spO2": null,
          "localSleepStartTimeInMillis": 1747001579000,
          "sleepNeed": 490,
          "bodyBatteryChange": 35,
          "gmtSleepStartTimeInMillis": 1746994379000,
          "gmtSleepEndTimeInMillis": 1747018559000,
          "hrvStatus": "UNBALANCED",
          "skinTempF": 0.6,
          "sleepScore": 61,
          "skinTempC": 0.4,
          "lightTime": 18600,
          "avgOvernightHrv": 39,
          "avgHeartRate": null,
          "hrv7dAverage": 46
        }
      },
      {
        "calendarDate": "2025-05-13",
        "values": {
          "remTime": 4560,
          "restingHeartRate": 52,
          "totalSleepTimeInSeconds": 27140,
          "respiration": 13,
          "localSleepEndTimeInMillis": 1747118329000,
          "deepTime": 2580,
          "awakeTime": 2280,
          "sleepScoreQuality": "FAIR",
          "spO2": null,
          "localSleepStartTimeInMillis": 1747088909000,
          "sleepNeed": 530,
          "bodyBatteryChange": 53,
          "gmtSleepStartTimeInMillis": 1747081709000,
          "gmtSleepEndTimeInMillis": 1747111129000,
          "hrvStatus": "UNBALANCED",
          "skinTempF": -0.5,
          "sleepScore": 78,
          "skinTempC": -0.3,
          "lightTime": 20040,
          "avgOvernightHrv": 50,
          "avgHeartRate": null,
          "hrv7dAverage": 46
        }
      }
    ]
  },
  "heart_rate": {
    "userProfilePK": 2405885,
    "calendarDate": "2025-05-13",
    "startTimestampGMT": "2025-05-12T22:00:00.0",
    "endTimestampGMT": "2025-05-13T22:00:00.0",
    "startTimestampLocal": "2025-05-13T00:00:00.0",
    "endTimestampLocal": "2025-05-14T00:00:00.0",
    "maxHeartRate": null,
    "minHeartRate": null,
    "restingHeartRate": 52,
    "lastSevenDaysAvgRestingHeartRate": 51,
    "heartRateValueDescriptors": null,
    "heartRateValues": null
  },
  "stress": {
    "userProfilePK": 2405885,
    "calendarDate": "2025-05-13",
    "startTimestampGMT": "2025-05-12T22:00:00.0",
    "endTimestampGMT": "2025-05-13T22:00:00.0",
    "startTimestampLocal": "2025-05-13T00:00:00.0",
    "endTimestampLocal": "2025-05-14T00:00:00.0",
    "maxStressLevel": 92,
    "avgStressLevel": 31,
    "stressChartValueOffset": 1,
    "stressChartYAxisOrigin": -1,
    "stressValueDescriptorsDTOList": [],
    "stressValuesArray": []
  },
  "body_battery_events": [
    {
      "event": {
        "eventType": "SLEEP",
        "eventStartTimeGmt": "2025-05-12T20:28:29.0",
        "timezoneOffset": 7200000,
        "durationInMilliseconds": 29400000,
        "bodyBatteryImpact": 53,
        "feedbackType": "NONE",
        "shortFeedback": "NONE"
      },
      "activityName": null,
      "activityType": null,
      "activityId": null,
      "averageStress": null,
      "stressValueDescriptorsDTOList": [],
      "stressValuesArray": [],
      "bodyBatteryValueDescriptorsDTOList": [],
      "bodyBatteryValuesArray": []
    },
    {
      "event": {
        "eventType": "ACTIVITY",
        "eventStartTimeGmt": "2025-05-13T05:15:53.0",
        "timezoneOffset": 7200000,
        "durationInMilliseconds": 4860000,
        "bodyBatteryImpact": -19,
        "feedbackType": "EXERCISE_TRAINING_EFFECT_3",
        "shortFeedback": "IMPROVING_AEROBIC_ENDURANCE"
      },
      "activityName": "Tarnowskie Góry Bieganie",
      "activityType": "running",
      "activityId": 19108237616,
      "averageStress": null,
      "stressValueDescriptorsDTOList": null,
      "stressValuesArray": null,
      "bodyBatteryValueDescriptorsDTOList": [],
      "bodyBatteryValuesArray": []
    }
  ],
  "daily_summary": {
    "userProfileId": 2405885,
    "totalKilocalories": 2733,
    "activeKilocalories": 957,
    "bmrKilocalories": 1776,
    "wellnessKilocalories": 2733,
    "burnedKilocalories": null,
    "consumedKilocalories": null,
    "remainingKilocalories": null,
    "totalSteps": 20576,
    "netCalorieGoal": null,
    "totalDistanceMeters": 17126,
    "wellnessDistanceMeters": 17126,
    "wellnessActiveKilocalories": 957,
    "netRemainingKilocalories": 957,
    "userDailySummaryId": 2405885,
    "calendarDate": "2025-05-13",
    "rule": {
      "typeId": 3,
      "typeKey": "subscribers"
    },
    "uuid": "85272f1b92944792b35932a3a8f91bb0",
    "dailyStepGoal": 16420,
    "wellnessStartTimeGmt": "2025-05-12T22:00:00.0",
    "wellnessStartTimeLocal": "2025-05-13T00:00:00.0",
    "wellnessEndTimeGmt": "2025-05-13T22:00:00.0",
    "wellnessEndTimeLocal": "2025-05-14T00:00:00.0",
    "durationInMilliseconds": 86400000,
    "wellnessDescription": null,
    "highlyActiveSeconds": 5360,
    "activeSeconds": 5630,
    "sedentarySeconds": 45051,
    "sleepingSeconds": 30359,
    "includesWellnessData": true,
    "includesActivityData": true,
    "includesCalorieConsumedData": false,
    "privacyProtected": false,
    "moderateIntensityMinutes": 3,
    "vigorousIntensityMinutes": 77,
    "floorsAscendedInMeters": 223.056,
    "floorsDescendedInMeters": 211.569,
    "floorsAscended": 73.1811,
    "floorsDescended": 69.4124,
    "intensityMinutesGoal": 150,
    "userFloorsAscendedGoal": 10,
    "minHeartRate": 46,
    "maxHeartRate": 171,
    "restingHeartRate": 52,
    "lastSevenDaysAvgRestingHeartRate": 51,
    "source": "GARMIN",
    "averageStressLevel": 31,
    "maxStressLevel": 92,
    "stressDuration": 28620,
    "restStressDuration": 30660,
    "activityStressDuration": 7440,
    "uncategorizedStressDuration": 18360,
    "totalStressDuration": 85080,
    "lowStressDuration": 19740,
    "mediumStressDuration": 7140,
    "highStressDuration": 1740,
    "stressPercentage": 33.64,
    "restStressPercentage": 36.04,
    "activityStressPercentage": 8.74,
    "uncategorizedStressPercentage": 21.58,
    "lowStressPercentage": 23.2,
    "mediumStressPercentage": 8.39,
    "highStressPercentage": 2.05,
    "stressQualifier": "BALANCED",
    "measurableAwakeDuration": 43260,
    "measurableAsleepDuration": 23460,
    "lastSyncTimestampGMT": null,
    "minAvgHeartRate": 48,
    "maxAvgHeartRate": 169,
    "bodyBatteryChargedValue": 46,
    "bodyBatteryDrainedValue": 60,
    "bodyBatteryHighestValue": 76,
    "bodyBatteryLowestValue": 16,
    "bodyBatteryMostRecentValue": 24,
    "bodyBatteryDuringSleep": 53,
    "bodyBatteryAtWakeTime": 76,
    "bodyBatteryVersion": 3,
    "abnormalHeartRateAlertsCount": null,
    "averageSpo2": null,
    "lowestSpo2": null,
    "latestSpo2": null,
    "latestSpo2ReadingTimeGmt": null,
    "latestSpo2ReadingTimeLocal": null,
    "averageMonitoringEnvironmentAltitude": 308,
    "restingCaloriesFromActivity": 85,
    "bodyBatteryDynamicFeedbackEvent": {
      "eventTimestampGmt": "2025-05-13T19:34:10",
      "bodyBatteryLevel": "MODERATE",
      "feedbackShortType": "SLEEP_PREPARATION_BALANCED_AND_INTENSIVE_EXERCISE",
      "feedbackLongType": "SLEEP_PREPARATION_BALANCED_AND_INTENSIVE_EXERCISE"
    },
    "endOfDayBodyBatteryDynamicFeedbackEvent": {
      "eventTimestampGmt": "2025-05-13T21:30:08",
      "bodyBatteryLevel": "MODERATE",
      "feedbackShortType": "SLEEP_TIME_PASSED_BALANCED_AND_INTENSIVE_EXERCISE",
      "feedbackLongType": "SLEEP_TIME_PASSED_BALANCED_AND_INTENSIVE_EXERCISE"
    },
    "bodyBatteryActivityEventList": [
      {
        "eventType": "SLEEP",
        "eventStartTimeGmt": "2025-05-12T20:28:29",
        "timezoneOffset": 7200000,
        "durationInMilliseconds": 29400000,
        "bodyBatteryImpact": 53,
        "feedbackType": "NONE",
        "shortFeedback": "NONE",
        "deviceId": 3450369454,
        "activityName": null,
        "activityType": null,
        "activityId": null,
        "eventUpdateTimeGmt": "2025-05-13T04:38:49"
      },
      {
        "eventType": "ACTIVITY",
        "eventStartTimeGmt": "2025-05-13T05:15:53",
        "timezoneOffset": 7200000,
        "durationInMilliseconds": 4860000,
        "bodyBatteryImpact": -19,
        "feedbackType": "EXERCISE_TRAINING_EFFECT_3",
        "shortFeedback": "IMPROVING_AEROBIC_ENDURANCE",
        "deviceId": 3450369454,
        "activityName": "Tarnowskie Góry Bieganie",
        "activityType": "running",
        "activityId": 19108237616,
        "eventUpdateTimeGmt": "2025-05-13T06:37:50"
      }
    ],
    "avgWakingRespirationValue": 16,
    "highestRespirationValue": 48,
    "lowestRespirationValue": 6,
    "latestRespirationValue": 13,
    "latestRespirationTimeGMT": "2025-05-13T21:59:00.0",
    "respirationAlgorithmVersion": 200
  },
  "daily_events": [
    {
      "userProfilePk": 2405885,
      "deviceId": 3450369454,
      "calendarDate": "2025-05-13",
      "startTimestampGMT": "2025-05-13T05:14:00.0",
      "endTimestampGMT": "2025-05-13T05:28:00.0",
      "duration": 14,
      "activityType": "running",
      "activitySubType": null,
      "startTimestampLocal": "2025-05-13T07:14:00.0",
      "endTimestampLocal": "2025-05-13T07:28:00.0",
      "moderateIntensityMinutes": 0,
      "vigorousIntensityMinutes": 10
    },
    {
      "userProfilePk": 2405885,
      "deviceId": 3450369454,
      "calendarDate": "2025-05-13",
      "startTimestampGMT": "2025-05-13T05:37:00.0",
      "endTimestampGMT": "2025-05-13T06:33:00.0",
      "duration": 56,
      "activityType": "running",
      "activitySubType": null,
      "startTimestampLocal": "2025-05-13T07:37:00.0",
      "endTimestampLocal": "2025-05-13T08:33:00.0",
      "moderateIntensityMinutes": 2,
      "vigorousIntensityMinutes": 53
    },
    {
      "userProfilePk": 2405885,
      "deviceId": 3450369454,
      "calendarDate": "2025-05-13",
      "startTimestampGMT": "2025-05-13T14:22:00.0",
      "endTimestampGMT": "2025-05-13T14:50:00.0",
      "duration": 28,
      "activityType": "walking",
      "activitySubType": null,
      "startTimestampLocal": "2025-05-13T16:22:00.0",
      "endTimestampLocal": "2025-05-13T16:50:00.0"
    },
    {
      "userProfilePk": 2405885,
      "deviceId": 3450369454,
      "calendarDate": "2025-05-13",
      "startTimestampGMT": "2025-05-13T15:36:00.0",
      "endTimestampGMT": "2025-05-13T16:06:00.0",
      "duration": 30,
      "activityType": "walking",
      "activitySubType": null,
      "startTimestampLocal": "2025-05-13T17:36:00.0",
      "endTimestampLocal": "2025-05-13T18:06:00.0"
    }
  ],
  "hrv": {
    "userProfilePk": 2405885,
    "hrvSummary": {
      "calendarDate": "2025-05-13",
      "weeklyAvg": 46,
      "lastNightAvg": 50,
      "lastNight5MinHigh": 68,
      "baseline": {
        "lowUpper": 44,
        "balancedLow": 48,
        "balancedUpper": 66,
        "markerValue": 0.18481445
      },
      "status": "UNBALANCED",
      "feedbackPhrase": "HRV_UNBALANCED_8",
      "createTimeStamp": "2025-05-13T04:38:53.754"
    },
    "hrvReadings": [],
    "startTimestampGMT": "2025-05-12T20:28:29.0",
    "endTimestampGMT": "2025-05-13T04:37:53.0",
    "startTimestampLocal": "2025-05-12T22:28:29.0",
    "endTimestampLocal": "2025-05-13T06:37:53.0",
    "sleepStartTimestampGMT": null,
    "sleepEndTimestampGMT": null,
    "sleepStartTimestampLocal": null,
    "sleepEndTimestampLocal": null
  },
  "training_readiness": [
    {
      "userProfilePK": 2405885,
      "calendarDate": "2025-05-13",
      "timestamp": "2025-05-13T06:37:50.0",
      "timestampLocal": "2025-05-13T08:37:50.0",
      "deviceId": 3450369454,
      "level": "POOR",
      "feedbackLong": "POOR_HRV_UNBALANCED",
      "feedbackShort": "TIME_TO_SLOW_DOWN",
      "score": 2,
      "sleepScore": 78,
      "sleepScoreFactorPercent": 67,
      "sleepScoreFactorFeedback": "MODERATE",
      "recoveryTime": 2850,
      "recoveryTimeFactorPercent": 31,
      "recoveryTimeFactorFeedback": "POOR",
      "acwrFactorPercent": 58,
      "acwrFactorFeedback": "MODERATE",
      "acuteLoad": 821,
      "stressHistoryFactorPercent": 85,
      "stressHistoryFactorFeedback": "GOOD",
      "hrvFactorPercent": 54,
      "hrvFactorFeedback": "MODERATE",
      "hrvWeeklyAverage": 46,
      "sleepHistoryFactorPercent": 48,
      "sleepHistoryFactorFeedback": "MODERATE",
      "validSleep": true,
      "inputContext": "AFTER_POST_EXERCISE_RESET",
      "primaryActivityTracker": true,
      "recoveryTimeChangePhrase": "NO_CHANGE_SLEEP"
    },
    {
      "userProfilePK": 2405885,
      "calendarDate": "2025-05-13",
      "timestamp": "2025-05-13T04:38:49.0",
      "timestampLocal": "2025-05-13T06:38:49.0",
      "deviceId": 3450369454,
      "level": "LOW",
      "feedbackLong": "LOW_HRV_UNBALANCED",
      "feedbackShort": "LISTEN_TO_YOUR_BODY",
      "score": 38,
      "sleepScore": 78,
      "sleepScoreFactorPercent": 67,
      "sleepScoreFactorFeedback": "MODERATE",
      "recoveryTime": 668,
      "recoveryTimeFactorPercent": 82,
      "recoveryTimeFactorFeedback": "GOOD",
      "acwrFactorPercent": 76,
      "acwrFactorFeedback": "GOOD",
      "acuteLoad": 608,
      "stressHistoryFactorPercent": 85,
      "stressHistoryFactorFeedback": "GOOD",
      "hrvFactorPercent": 54,
      "hrvFactorFeedback": "MODERATE",
      "hrvWeeklyAverage": 46,
      "sleepHistoryFactorPercent": 48,
      "sleepHistoryFactorFeedback": "MODERATE",
      "validSleep": true,
      "inputContext": "AFTER_WAKEUP_RESET",
      "primaryActivityTracker": true,
      "recoveryTimeChangePhrase": "NO_CHANGE_SLEEP"
    },
    {
      "userProfilePK": 2405885,
      "calendarDate": "2025-05-13",
      "timestamp": "2025-05-12T22:11:53.0",
      "timestampLocal": "2025-05-13T00:11:53.0",
      "deviceId": 3450369454,
      "level": "LOW",
      "feedbackLong": "LOW_HRV_UNBALANCED",
      "feedbackShort": "LISTEN_TO_YOUR_BODY",
      "score": 34,
      "sleepScore": null,
      "sleepScoreFactorPercent": 0,
      "sleepScoreFactorFeedback": "NONE",
      "recoveryTime": 1058,
      "recoveryTimeFactorPercent": 72,
      "recoveryTimeFactorFeedback": "GOOD",
      "acwrFactorPercent": 76,
      "acwrFactorFeedback": "GOOD",
      "acuteLoad": 742,
      "stressHistoryFactorPercent": 72,
      "stressHistoryFactorFeedback": "GOOD",
      "hrvFactorPercent": 49,
      "hrvFactorFeedback": "MODERATE",
      "hrvWeeklyAverage": 46,
      "sleepHistoryFactorPercent": 48,
      "sleepHistoryFactorFeedback": "MODERATE",
      "validSleep": false,
      "inputContext": "UPDATE_REALTIME_VARIABLES",
      "primaryActivityTracker": true,
      "recoveryTimeChangePhrase": null
    }
  ],
  "vo2max": {
    "userId": 2405885,
    "generic": {
      "calendarDate": "2026-05-06",
      "vo2MaxPreciseValue": 57.6,
      "vo2MaxValue": 58,
      "fitnessAge": null,
      "fitnessAgeDescription": null,
      "maxMetCategory": 0
    },
    "cycling": null,
    "heatAltitudeAcclimation": {
      "calendarDate": "2025-05-13",
      "altitudeAcclimationDate": "2025-05-13",
      "previousAltitudeAcclimationDate": "2025-05-13",
      "heatAcclimationDate": "2025-05-13",
      "previousHeatAcclimationDate": "2025-05-12",
      "altitudeAcclimation": 0,
      "previousAltitudeAcclimation": 0,
      "heatAcclimationPercentage": 1,
      "previousHeatAcclimationPercentage": 2,
      "heatTrend": "DEACCLIMATIZING",
      "altitudeTrend": null,
      "currentAltitude": 321,
      "previousAltitude": 0,
      "acclimationPercentage": 0,
      "previousAcclimationPercentage": 0,
      "altitudeAcclimationLocalTimestamp": "2025-05-13T23:56:21.0"
    }
  },
  "spo2": {
    "userProfilePK": 2405885,
    "calendarDate": "2025-05-13",
    "deviceId": null,
    "sleepMeasurementStartGMT": null,
    "sleepMeasurementEndGMT": null,
    "numberOfEventsBelowThreshold": null,
    "durationOfEventsBelowThreshold": null,
    "alertThresholdValue": null,
    "averageSpO2": null,
    "averageSpO2HR": null,
    "lowestSpO2": null,
    "spo2ValueDescriptorsDTOList": [],
    "spo2ValuesArray": []
  }
}